{
	"Changes": [
		{
            "Action": "EditData",
            "Target": "Data/Weapons",
            "Entries": {
			"maat.BetterThings_Wooden_Sword": {
				"Name": "Wooden Sword",
				"DisplayName": "{{i18n:woodensword.1}}",
				"Description": "{{i18n:woodensword.2}}",
				"Type": 3,
				"Category": -98,
				"Price": 16000,
				"MinDamage": 12,
				"MaxDamage": 26,
				"Knockback": 0.2,
				"AreaOfEffect": 0,
				"CritChance": 0.05,
				"Speed": 0,
				"Precision": 1.0,
				"Defense": 0.4,
				"Texture": "{{InternalAssetKey: assets/wooden_sword.png}}",
				"SpriteIndex": 0,
				"CanBeLostOnDeath": true,
				"CustomFields": {}
				}
			}
		},
		{
            "Action": "EditData",
            "Target": "Data/Weapons",
            "Entries": {
			"maat.BetterThings_Prismarine_Sword": {
				"Name": "Prismarine Sword",
				"DisplayName": "{{i18n:prismarinesword.1}}",
				"Description": "{{i18n:prismarinesword.2}}",
				"Type": 3,
				"Category": -98,
				"Price": 24000,
				"MinDamage": 19,
				"MaxDamage": 29,
				"Knockback": 0.3,
				"AreaOfEffect": 0,
				"CritChance": 0.07,
				"Speed": 0.1,
				"Precision": 1.3,
				"Defense": 0.8,
				"Texture": "{{InternalAssetKey: assets/prismarine_sword.png}}",
				"SpriteIndex": 0,
				"CanBeLostOnDeath": false,
				"CustomFields": {}
				}
			}
		},
        {
            "Action": "EditData",
            "Target": "Data/Weapons",
            "Entries": {
			"maat.BetterThings_Iron_Sword": {
				"Name": "Iron Sword",
				"DisplayName": "{{i18n:ironsword.1}}",
				"Description": "{{i18n:ironsword.2}}",
				"Type": 3,
				"Category": -98,
				"Price": 32000,
				"MinDamage": 24,
				"MaxDamage": 39,
				"Knockback": 0.3,
				"AreaOfEffect": 0,
				"CritChance": 0.06,
				"Speed": 0.1,
				"Precision": 1.1,
				"Defense": 0.6,
				"Texture": "{{InternalAssetKey: assets/iron_sword.png}}",
				"SpriteIndex": 0,
				"CanBeLostOnDeath": false,
				"CustomFields": {}
				}
			}
		},
        {
            "Action": "EditData",
            "Target": "Data/Weapons",
            "Entries": {
			"maat.BetterThings_Golden_Sword": {
				"Name": "Golden Sword",
				"DisplayName": "{{i18n:golden_sword.1}}",
				"Description": "{{i18n:golden_sword.2}}",
				"Type": 3,
				"Category": -98,
				"Price": 64000,
				"MinDamage": 39,
				"MaxDamage": 49,
				"Knockback": 0.4,
				"AreaOfEffect": 0,
				"CritChance": 0.07,
				"Speed": 0.2,
				"Precision": 1.2,
				"Defense": 0.6,
				"Texture": "{{InternalAssetKey: assets/golden_sword.png}}",
				"SpriteIndex": 0,
				"CanBeLostOnDeath": true,
				"CustomFields": {}
				}
			}
		},
		{
            "Action": "EditData",
            "Target": "Data/Weapons",
            "Entries": {
			"maat.BetterThings_Emerald_Sword": {
				"Name": "Emerald Sword",
				"DisplayName": "{{i18n:emeraldsword.1}}",
				"Description": "{{i18n:emeraldsword.2}}",
				"Type": 3,
				"Category": -98,
				"Price": 82000,
				"MinDamage": 49,
				"MaxDamage": 59,
				"Knockback": 0.4,
				"AreaOfEffect": 0,
				"CritChance": 0.1,
				"Speed": 0.2,
				"Precision": 1.5,
				"Defense": 0.7,
				"Texture": "{{InternalAssetKey: assets/emerald_sword.png}}",
				"SpriteIndex": 0,
				"CanBeLostOnDeath": true,
				"CustomFields": {}
				}
			}
		},
		{
            "Action": "EditData",
            "Target": "Data/Weapons",
            "Entries": {
			"maat.BetterThings_Amethyst_Sword": {
				"Name": "Amethyst Sword",
				"DisplayName": "{{i18n:amethystsword.1}}",
				"Description": "{{i18n:amethystsword.2}}",
				"Type": 3,
				"Category": -98,
				"Price": 87000,
				"MinDamage": 45,
				"MaxDamage": 62,
				"Knockback": 0.4,
				"AreaOfEffect": 0,
				"CritChance": 0.15,
				"Speed": 0.25,
				"Precision": 1.5,
				"Defense": 1.0,
				"Texture": "{{InternalAssetKey: assets/amethyst_sword.png}}",
				"SpriteIndex": 0,
				"CanBeLostOnDeath": true,
				"CustomFields": {}
				}
			}
		},
		{
            "Action": "EditData",
            "Target": "Data/Weapons",
            "Entries": {
			"maat.BetterThings_Ruby_Sword": {
				"Name": "Ruby Sword",
				"DisplayName": "{{i18n:rubysword.1}}",
				"Description": "{{i18n:rubysword.2}}",
				"Type": 3,
				"Category": -98,
				"Price": 92000,
				"MinDamage": 50,
				"MaxDamage": 62,
				"Knockback": 0.5,
				"AreaOfEffect": 0,
				"CritChance": 0.19,
				"Speed": 0.3,
				"Precision": 2.0,
				"Defense": 1.5,
				"Texture": "{{InternalAssetKey: assets/ruby_sword.png}}",
				"SpriteIndex": 0,
				"CanBeLostOnDeath": true,
				"CustomFields": {}
				}
			}
		},
		{
            "Action": "EditData",
            "Target": "Data/Weapons",
            "Entries": {
			"maat.BetterThings_Blossom_Sword": {
				"Name": "Blossom Sword",
				"DisplayName": "{{i18n:blossomsword.1}}",
				"Description": "{{i18n:blossomsword.2}}",
				"Type": 3,
				"Category": -98,
				"Price": 100000,
				"MinDamage": 65,
				"MaxDamage": 79,
				"Knockback": 0.5,
				"AreaOfEffect": 0,
				"CritChance": 0.2,
				"Speed": 0.4,
				"Precision": 2.1,
				"Defense": 1.5,
				"Texture": "{{InternalAssetKey: assets/blossom_sword.png}}",
				"SpriteIndex": 0,
				"CanBeLostOnDeath": true,
				"CustomFields": {}
				}
			}
		},
        {
            "Action": "EditData",
            "Target": "Data/Weapons",
            "Entries": {
			"maat.BetterThings_Diamond_Sword": {
				"Name": "Diamond Sword",
				"DisplayName": "{{i18n:diamondsword.1}}",
				"Description": "{{i18n:diamondsword.2}}",
				"Type": 3,
				"Category": -98,
				"Price": 128000,
				"MinDamage": 69,
				"MaxDamage": 89,
				"Knockback": 0.5,
				"AreaOfEffect": 0.2,
				"CritChance": 0.3,
				"Speed": 5.0,
				"Precision": 1.3,
				"Defense": 1.0,
				"Texture": "{{InternalAssetKey: assets/diamond_sword.png}}",
				"SpriteIndex": 0,
				"CanBeLostOnDeath": false,
				"CustomFields": {}
				}
			}
		},
		{
            "Action": "EditData",
            "Target": "Data/Weapons",
            "Entries": {
			"maat.BetterThings_Wooden_Dagger": {
				"Name": "Wooden Dagger",
				"DisplayName": "{{i18n:woodendagger.1}}",
				"Description": "{{i18n:woodendagger.2}}",
				"Type": 1,
				"Category": -98,
				"Price": 12000,
				"MinDamage": 10,
				"MaxDamage": 22,
				"Knockback": 0.5,
				"AreaOfEffect": 0,
				"MineBaseLevel": 80,
                "MineMinLevel": 50,
				"CritChance": 0.04,
				"CritMultiplier": 3.0,
				"Speed": 0,
				"Precision": 0,
				"Defense": 0,
				"Texture": "{{InternalAssetKey: assets/wooden_dagger.png}}",
				"SpriteIndex": 0,
				"CanBeLostOnDeath": true,
				"CustomFields": {}
				}
			}
		},
		{
            "Action": "EditData",
            "Target": "Data/Weapons",
            "Entries": {
			"maat.BetterThings_Prismarine_Dagger": {
				"Name": "Prismarine Dagger",
				"DisplayName": "{{i18n:prismarine_dagger.1}}",
				"Description": "{{i18n:prismarine_dagger.2}}",
				"Type": 1,
				"Category": -98,
				"Price": 20000,
				"MinDamage": 15,
				"MaxDamage": 30,
				"Knockback": 0.5,
				"AreaOfEffect": 0,
				"MineBaseLevel": 80,
                "MineMinLevel": 50,
				"CritChance": 0.1,
				"CritMultiplier": 4.5,
				"Speed": 0.1,
				"Precision": 0,
				"Defense": 0.1,
				"Texture": "{{InternalAssetKey: assets/prismarine_dagger.png}}",
				"SpriteIndex": 0,
				"CanBeLostOnDeath": true,
				"CustomFields": {}
				}
			}
		},
		{
            "Action": "EditData",
            "Target": "Data/Weapons",
            "Entries": {
			"maat.BetterThings_Iron_Dagger": {
				"Name": "Iron Dagger",
				"DisplayName": "{{i18n:irondagger.1}}",
				"Description": "{{i18n:irondagger.2}}",
				"Type": 1,
				"Category": -98,
				"Price": 24000,
				"MinDamage": 23,
				"MaxDamage": 33,
				"Knockback": 0.6,
				"AreaOfEffect": 0,
				"MineBaseLevel": 80,
                "MineMinLevel": 50,
				"CritChance": 0.05,
				"CritMultiplier": 4.0,
				"Speed": 0,
				"Precision": 0,
				"Defense": 0,
				"Texture": "{{InternalAssetKey: assets/iron_dagger.png}}",
				"SpriteIndex": 0,
				"CanBeLostOnDeath": true,
				"CustomFields": {}
				}
			}
		},
		{
            "Action": "EditData",
            "Target": "Data/Weapons",
            "Entries": {
			"maat.BetterThings_Golden_Dagger": {
				"Name": "Golden Dagger",
				"DisplayName": "{{i18n:golden_dagger.1}}",
				"Description": "{{i18n:golden_dagger.2}}",
				"Type": 1,
				"Category": -98,
				"Price": 48000,
				"MinDamage": 35,
				"MaxDamage": 45,
				"Knockback": 0.7,
				"AreaOfEffect": 0,
				"MineBaseLevel": -1,
                "MineMinLevel": -1,
				"CritChance": 0.06,
				"CritMultiplier": 5.0,
				"Speed": 0,
				"Precision": 0,
				"Defense": 0,
				"Texture": "{{InternalAssetKey: assets/golden_dagger.png}}",
				"SpriteIndex": 0,
				"CanBeLostOnDeath": true,
				"CustomFields": {}
				}
			}
		},
		{
            "Action": "EditData",
            "Target": "Data/Weapons",
            "Entries": {
			"maat.BetterThings_Emerald_Dagger": {
				"Name": "Emerald Dagger",
				"DisplayName": "{{i18n:emerald_dagger.1}}",
				"Description": "{{i18n:emerald_dagger.2}}",
				"Type": 1,
				"Category": -98,
				"Price": 50000,
				"MinDamage": 37,
				"MaxDamage": 47,
				"Knockback": 0.8,
				"AreaOfEffect": 0,
				"MineBaseLevel": -1,
                "MineMinLevel": -1,
				"CritChance": 0.07,
				"CritMultiplier": 6.0,
				"Speed": 0,
				"Precision": 0.1,
				"Defense": 0,
				"Texture": "{{InternalAssetKey: assets/emerald_dagger.png}}",
				"SpriteIndex": 0,
				"CanBeLostOnDeath": true,
				"CustomFields": {}
				}
			}
		},
		{
            "Action": "EditData",
            "Target": "Data/Weapons",
            "Entries": {
			"maat.BetterThings_Amethyst_Dagger": {
				"Name": "Amethyst Dagger",
				"DisplayName": "{{i18n:amethyst_dagger.1}}",
				"Description": "{{i18n:amethyst_dagger.2}}",
				"Type": 1,
				"Category": -98,
				"Price": 53000,
				"MinDamage": 40,
				"MaxDamage": 50,
				"Knockback": 0.9,
				"AreaOfEffect": 0,
				"MineBaseLevel": -1,
                "MineMinLevel": -1,
				"CritChance": 0.08,
				"CritMultiplier": 7.0,
				"Speed": 0,
				"Precision": 0.2,
				"Defense": 0,
				"Texture": "{{InternalAssetKey: assets/amethyst_dagger.png}}",
				"SpriteIndex": 0,
				"CanBeLostOnDeath": true,
				"CustomFields": {}
				}
			}
		},
		{
            "Action": "EditData",
            "Target": "Data/Weapons",
            "Entries": {
			"maat.BetterThings_Ruby_Dagger": {
				"Name": "Ruby Dagger",
				"DisplayName": "{{i18n:ruby_dagger.1}}",
				"Description": "{{i18n:ruby_dagger.2}}",
				"Type": 1,
				"Category": -98,
				"Price": 56000,
				"MinDamage": 43,
				"MaxDamage": 53,
				"Knockback": 1.0,
				"AreaOfEffect": 0,
				"MineBaseLevel": -1,
                "MineMinLevel": -1,
				"CritChance": 0.09,
				"CritMultiplier": 8.0,
				"Speed": 0,
				"Precision": 0.3,
				"Defense": 0,
				"Texture": "{{InternalAssetKey: assets/ruby_dagger.png}}",
				"SpriteIndex": 0,
				"CanBeLostOnDeath": true,
				"CustomFields": {}
				}
			}
		},
		{
            "Action": "EditData",
            "Target": "Data/Weapons",
            "Entries": {
			"maat.BetterThings_Blossom_Dagger": {
				"Name": "Blossom Dagger",
				"DisplayName": "{{i18n:blossom_dagger.1}}",
				"Description": "{{i18n:blossom_dagger.2}}",
				"Type": 1,
				"Category": -98,
				"Price": 60000,
				"MinDamage": 50,
				"MaxDamage": 61,
				"Knockback": 0.5,
				"AreaOfEffect": 0,
				"MineBaseLevel": -1,
                "MineMinLevel": -1,
				"CritChance": 0.1,
				"CritMultiplier": 9.0,
				"Speed": 0.1,
				"Precision": 0.4,
				"Defense": 0,
				"Texture": "{{InternalAssetKey: assets/blossom_dagger.png}}",
				"SpriteIndex": 0,
				"CanBeLostOnDeath": true,
				"CustomFields": {}
				}
			}
		},
		{
            "Action": "EditData",
            "Target": "Data/Weapons",
            "Entries": {
			"maat.BetterThings_Diamond_Dagger": {
				"Name": "Diamond Dagger",
				"DisplayName": "{{i18n:diamond_dagger.1}}",
				"Description": "{{i18n:diamond_dagger.2}}",
				"Type": 1,
				"Category": -98,
				"Price": 96000,
				"MinDamage": 45,
				"MaxDamage": 65,
				"Knockback": 0.8,
				"AreaOfEffect": 0,
				"MineBaseLevel": -1,
                "MineMinLevel": -1,
				"CritChance": 0.11,
				"CritMultiplier": 9.5,
				"Speed": 0,
				"Precision": 10,
				"Defense": 1,
				"Texture": "{{InternalAssetKey: assets/diamond_dagger.png}}",
				"SpriteIndex": 0,
				"CanBeLostOnDeath": true,
				"CustomFields": {}
				}
			}
		},
		{
            "Action": "EditData",
            "Target": "Data/Weapons",
            "Entries": {
			"maat.BetterThings_Diamond_Dagger": {
				"Name": "Diamond Dagger",
				"DisplayName": "{{i18n:diamond_dagger.1}}",
				"Description": "{{i18n:diamond_dagger.2}}",
				"Type": 1,
				"Category": -98,
				"Price": 96000,
				"MinDamage": 42,
				"MaxDamage": 60,
				"Knockback": 0.8,
				"AreaOfEffect": 0,
				"MineBaseLevel": -1,
                "MineMinLevel": -1,
				"CritChance": 0.1,
				"CritMultiplier": 6.0,
				"Speed": 0,
				"Precision": 10,
				"Defense": 1,
				"Texture": "{{InternalAssetKey: assets/diamond_dagger.png}}",
				"SpriteIndex": 0,
				"CanBeLostOnDeath": true,
				"CustomFields": {}
				}
			}
		},
		{
		"Action": "EditData",
        "Target": "Data/Objects",
        "Entries": {
		"maat.BetterThings_Popcorn":  {
        "Name": "Popcorn",
        "DisplayName": "{{i18n:popcorn.1}}",
        "Description": "{{i18n:popcorn.2}}",
        "Type": "Cooking",
        "Category": -7,
        "Price": 450,
        "Texture": "{{InternalAssetKey: assets/popcorn.png}}",
        "SpriteIndex": 0,
		"Edibility": 12,
        "IsDrink": false,
        "Buffs": [
      {
        "Id": "Food",
        "BuffId": null,
        "IconTexture": null,
        "IconSpriteIndex": 0,
        "Duration": 600,
        "IsDebuff": false,
        "GlowColor": null,
        "CustomAttributes": {
          "FarmingLevel": 0.0,
          "FishingLevel": 0.0,
          "MiningLevel": 0.0,
          "LuckLevel": 0.0,
          "ForagingLevel": 0.0,
          "MaxStamina": 10.0,
          "MagneticRadius": 0.0,
          "Speed": 1.0,
          "Defense": 0.0,
          "Attack": 0.0
        },
        "CustomFields": null
      }
    ],
    "GeodeDropsDefaultItems": false,
    "GeodeDrops": null,
    "ArtifactSpotChances": null,
    "CanBeGivenAsGift": true,
    "CanBeTrashed": true,
    "ExcludeFromFishingCollection": false,
    "ExcludeFromShippingCollection": false,
    "ExcludeFromRandomSale": false,
    "ContextTags": [
      "color_yellow",
      "food_party"
      ],
    "CustomFields": {}
          }
        }
      },
	  {
		"Action": "EditData",
        "Target": "Data/Objects",
        "Entries": {
		"maat.BetterThings_Piece_Of_Pizza":  {
        "Name": "Piece of Pizza",
        "DisplayName": "{{i18n:piece_of_pizza.1}}",
        "Description": "{{i18n:piece_of_pizza.2}}",
        "Type": "Cooking",
        "Category": -7,
        "Price": 400,
        "Texture": "{{InternalAssetKey: assets/piece_of_pizza.png}}",
        "SpriteIndex": 0,
		"Edibility": 8,
        "IsDrink": false,
        "Buffs": [
      {
        "Id": "Food",
        "BuffId": null,
        "IconTexture": null,
        "IconSpriteIndex": 0,
        "Duration": 300,
        "IsDebuff": false,
        "GlowColor": null,
        "CustomAttributes": {
          "FarmingLevel": 0.0,
          "FishingLevel": 0.0,
          "MiningLevel": 0.0,
          "LuckLevel": 0.0,
          "ForagingLevel": 0.0,
          "MaxStamina": 2.0,
          "MagneticRadius": 0.0,
          "Speed": 1.0,
          "Defense": 0.0,
          "Attack": 0.0
        },
        "CustomFields": null
      }
    ],
    "GeodeDropsDefaultItems": false,
    "GeodeDrops": null,
    "ArtifactSpotChances": null,
    "CanBeGivenAsGift": true,
    "CanBeTrashed": true,
    "ExcludeFromFishingCollection": false,
    "ExcludeFromShippingCollection": false,
    "ExcludeFromRandomSale": false,
    "ContextTags": [
      "color_yellow",
      "food_party"
      ],
    "CustomFields": {}
          }
        }
      },
	  {
		"Action": "EditData",
        "Target": "Data/Objects",
        "Entries": {
		"maat.BetterThings_Donut":  {
        "Name": "Donut",
        "DisplayName": "{{i18n:donut.1}}",
        "Description": "{{i18n:donut.2}}",
        "Type": "Cooking",
        "Category": -7,
        "Price": 8100,
        "Texture": "{{InternalAssetKey: assets/donut.png}}",
        "SpriteIndex": 0,
		"Edibility": 20,
        "IsDrink": false,
        "Buffs": [
      {
        "Id": "Food",
        "BuffId": null,
        "IconTexture": null,
        "IconSpriteIndex": 0,
        "Duration": 400,
        "IsDebuff": false,
        "GlowColor": null,
        "CustomAttributes": {
          "FarmingLevel": 0.0,
          "FishingLevel": 0.0,
          "MiningLevel": 0.0,
          "LuckLevel": 0.0,
          "ForagingLevel": 0.0,
          "MaxStamina": 20.0,
          "MagneticRadius": 0.0,
          "Speed": 10.0,
          "Defense": 0.0,
          "Attack": 0.0
        },
        "CustomFields": null
      }
    ],
    "GeodeDropsDefaultItems": false,
    "GeodeDrops": null,
    "ArtifactSpotChances": null,
    "CanBeGivenAsGift": true,
    "CanBeTrashed": true,
    "ExcludeFromFishingCollection": false,
    "ExcludeFromShippingCollection": false,
    "ExcludeFromRandomSale": false,
    "ContextTags": [
      "color_pink",
	  "color_brown",
      "food_party"
      ],
    "CustomFields": {}
          }
        }
      },
	  {
		"Action": "EditData",
        "Target": "Data/Objects",
        "Entries": {
		"maat.BetterThings_Onigiri":  {
        "Name": "Onigiri",
        "DisplayName": "{{i18n:onigiri.1}}",
        "Description": "{{i18n:onigiri.2}}",
        "Type": "Cooking",
        "Category": -7,
        "Price": 1200,
        "Texture": "{{InternalAssetKey: assets/onigiri.png}}",
        "SpriteIndex": 0,
		"Edibility": 30,
        "IsDrink": false,
        "Buffs": [
      {
        "Id": "Food",
        "BuffId": null,
        "IconTexture": null,
        "IconSpriteIndex": 0,
        "Duration": 360,
        "IsDebuff": false,
        "GlowColor": null,
        "CustomAttributes": {
          "FarmingLevel": 0.0,
          "FishingLevel": 3.0,
          "MiningLevel": 0.0,
          "LuckLevel": 2.0,
          "ForagingLevel": 0.0,
          "MaxStamina": 25.0,
          "MagneticRadius": 0.0,
          "Speed": 0.0,
          "Defense": 0.0,
          "Attack": 0.0
        },
        "CustomFields": null
      }
    ],
    "GeodeDropsDefaultItems": false,
    "GeodeDrops": null,
    "ArtifactSpotChances": null,
    "CanBeGivenAsGift": true,
    "CanBeTrashed": true,
    "ExcludeFromFishingCollection": false,
    "ExcludeFromShippingCollection": false,
    "ExcludeFromRandomSale": false,
    "ContextTags": [
      "color_white",
      "food_party"
      ],
    "CustomFields": {}
          }
        }
      },
	  {
		"Action": "EditData",
        "Target": "Data/Objects",
        "Entries": {
		"maat.BetterThings_Pretzel":  {
        "Name": "Pretzel",
        "DisplayName": "{{i18n:pretzel.1}}",
        "Description": "{{i18n:pretzel.2}}",
        "Type": "Cooking",
        "Category": -7,
        "Price": 300,
        "Texture": "{{InternalAssetKey: assets/pretzel.png}}",
        "SpriteIndex": 0,
		"Edibility": 35,
        "IsDrink": false,
        "Buffs": [
      {
        "Id": "Food",
        "BuffId": null,
        "IconTexture": null,
        "IconSpriteIndex": 0,
        "Duration": 300,
        "IsDebuff": false,
        "GlowColor": null,
        "CustomAttributes": {
          "FarmingLevel": 0.0,
          "FishingLevel": 0.0,
          "MiningLevel": 1.0,
          "LuckLevel": 0.0,
          "ForagingLevel": 0.0,
          "MaxStamina": 30.0,
          "MagneticRadius": 0.0,
          "Speed": 2.0,
          "Defense": 0.0,
          "Attack": 1.0
        },
        "CustomFields": null
      }
    ],
    "GeodeDropsDefaultItems": false,
    "GeodeDrops": null,
    "ArtifactSpotChances": null,
    "CanBeGivenAsGift": true,
    "CanBeTrashed": true,
    "ExcludeFromFishingCollection": false,
    "ExcludeFromShippingCollection": false,
    "ExcludeFromRandomSale": false,
    "ContextTags": [
      "color_brown",
      "food_party"
      ],
    "CustomFields": {}
          }
        }
      },
	  {
		"Action": "EditData",
        "Target": "Data/Objects",
        "Entries": {
		"maat.BetterThings_TruffleCookie":  {
        "Name": "Truffle Cookie",
        "DisplayName": "{{i18n:trufflecookie.1}}",
        "Description": "{{i18n:trufflecookie.2}}",
        "Type": "Cooking",
        "Category": -7,
        "Price": 1255,
        "Texture": "{{InternalAssetKey: assets/truffle_cookie.png}}",
        "SpriteIndex": 0,
		"Edibility": 50,
        "IsDrink": false,
        "Buffs": [
      {
        "Id": "Food",
        "BuffId": null,
        "IconTexture": null,
        "IconSpriteIndex": 0,
        "Duration": 100,
        "IsDebuff": false,
        "GlowColor": null,
        "CustomAttributes": {
          "FarmingLevel": 2.0,
          "FishingLevel": 0.0,
          "MiningLevel": 0.0,
          "LuckLevel": 2.0,
          "ForagingLevel": 2.0,
          "MaxStamina": 50.0,
          "MagneticRadius": 64.0,
          "Speed": 3.0,
          "Defense": 0.0,
          "Attack": 0.0
        },
        "CustomFields": null
      }
    ],
    "GeodeDropsDefaultItems": false,
    "GeodeDrops": null,
    "ArtifactSpotChances": null,
    "CanBeGivenAsGift": true,
    "CanBeTrashed": true,
    "ExcludeFromFishingCollection": false,
    "ExcludeFromShippingCollection": false,
    "ExcludeFromRandomSale": false,
    "ContextTags": [
      "color_brown",
      "food_party"
      ],
    "CustomFields": {}
          }
        }
      },
	   {
		"Action": "EditData",
        "Target": "Data/Objects",
        "Entries": {
		"maat.BetterThings_BlueberryMuffin":  {
        "Name": "Blueberry Muffin",
        "DisplayName": "{{i18n:blueberrymuffin.1}}",
        "Description": "{{i18n:blueberrymuffin.2}}",
        "Type": "Cooking",
        "Category": -7,
        "Price": 475,
        "Texture": "{{InternalAssetKey: assets/muffin.png}}",
        "SpriteIndex": 0,
		"Edibility": 30,
        "IsDrink": false,
        "Buffs": [
      {
        "Id": "Food",
        "BuffId": null,
        "IconTexture": null,
        "IconSpriteIndex": 0,
        "Duration": 200,
        "IsDebuff": false,
        "GlowColor": null,
        "CustomAttributes": {
          "FarmingLevel": 1.0,
          "FishingLevel": 0.0,
          "MiningLevel": 0.0,
          "LuckLevel": 1.0,
          "ForagingLevel": 0.0,
          "MaxStamina": 25.0,
          "MagneticRadius": 20.0,
          "Speed": 2.0,
          "Defense": 0.0,
          "Attack": 0.0
        },
        "CustomFields": null
      }
    ],
    "GeodeDropsDefaultItems": false,
    "GeodeDrops": null,
    "ArtifactSpotChances": null,
    "CanBeGivenAsGift": true,
    "CanBeTrashed": true,
    "ExcludeFromFishingCollection": false,
    "ExcludeFromShippingCollection": false,
    "ExcludeFromRandomSale": false,
    "ContextTags": [
      "color_brown",
	  "color_blue",
      "food_party"
      ],
    "CustomFields": {}
          }
        }
      },
	  {
		"Action": "EditData",
        "Target": "Data/Objects",
        "Entries": {
		"{{ModId}}_BlossomSapling":  {
    "Name": "{{ModId}}_BlossomSapling",
    "DisplayName": "{{i18n:blossomsapling.name}}",
    "Description": "{{i18n:blossomsapling.description}}",
    "Type": "Basic",
    "Category": -74,
    "Price": 1000,
    "Texture": "{{InternalAssetKey: assets/blossom_sapling.png}}",
    "SpriteIndex": 0,
    "Edibility": -300,
    "IsDrink": false,
    "Buffs": null,
    "GeodeDropsDefaultItems": false,
    "GeodeDrops": null,
    "ArtifactSpotChances": null,
    "CanBeGivenAsGift": true,
    "CanBeTrashed": true,
    "ExcludeFromFishingCollection": false,
    "ExcludeFromShippingCollection": false,
    "ExcludeFromRandomSale": false,
    "ContextTags": [
	"season_spring"
	],
    "CustomFields": null
          }
        }
      },
	  {
		"Action": "EditData",
        "Target": "Data/Objects",
        "Entries": {
		"{{ModId}}_CoconutSapling":  {
    "Name": "{{ModId}}_CoconutSapling",
    "DisplayName": "{{i18n:coconutsapling.name}}",
    "Description": "{{i18n:coconutsapling.description}}",
    "Type": "Basic",
    "Category": -74,
    "Price": 1000,
    "Texture": "{{InternalAssetKey: assets/coconut_sapling.png}}",
    "SpriteIndex": 0,
    "Edibility": -300,
    "IsDrink": false,
    "Buffs": null,
    "GeodeDropsDefaultItems": false,
    "GeodeDrops": null,
    "ArtifactSpotChances": null,
    "CanBeGivenAsGift": true,
    "CanBeTrashed": true,
    "ExcludeFromFishingCollection": false,
    "ExcludeFromShippingCollection": false,
    "ExcludeFromRandomSale": false,
    "ContextTags": [
	"season_spring",
	"season_summer",
	"season_fall"
	],
    "CustomFields": null
          }
        }
      },
	   {
		"Action": "EditData",
        "Target": "Data/Objects",
        "Entries": {
		"{{ModId}}_GoldenCoconutSapling":  {
    "Name": "{{ModId}}_GoldenCoconutSapling",
    "DisplayName": "{{i18n:goldencoconutsapling.name}}",
    "Description": "{{i18n:goldencoconutsapling.description}}",
    "Type": "Basic",
    "Category": -74,
    "Price": 1000,
    "Texture": "{{InternalAssetKey: assets/goldencoconut_sapling.png}}",
    "SpriteIndex": 0,
    "Edibility": -300,
    "IsDrink": false,
    "Buffs": null,
    "GeodeDropsDefaultItems": false,
    "GeodeDrops": null,
    "ArtifactSpotChances": null,
    "CanBeGivenAsGift": true,
    "CanBeTrashed": true,
    "ExcludeFromFishingCollection": false,
    "ExcludeFromShippingCollection": false,
    "ExcludeFromRandomSale": false,
    "ContextTags": [
	"season_summer"
	],
    "CustomFields": null
          }
        }
      },
	  {
		"Action": "EditData",
        "Target": "Data/Objects",
        "Entries": {
		"{{ModId}}_BlossomFruit":  {
	"Name": "{{ModId}}_BlossomFruit",
    "DisplayName": "{{i18n:blossomfruit.name}}",
    "Description": "{{i18n:blossomfruit.description}}",
    "Type": "Basic",
    "Category": -79,
    "Price": 250,
    "Texture": "{{InternalAssetKey: assets/blossom_fruit.png}}",
    "SpriteIndex": 0,
    "Edibility": 15,
    "IsDrink": false,
    "Buffs": null,
    "GeodeDropsDefaultItems": false,
    "GeodeDrops": null,
    "ArtifactSpotChances": null,
    "CanBeGivenAsGift": true,
    "CanBeTrashed": true,
    "ExcludeFromFishingCollection": false,
    "ExcludeFromShippingCollection": false,
    "ExcludeFromRandomSale": false,
    "ContextTags": [
      "fruit_item",
      "fruit_tree_item",
      "season_spring"
    ],
    "CustomFields": null
         }
	   }
	 },
	 {
	  "Action": "EditData",
      "Target": "Data/Objects",
      "Entries": {
	  "maat.BetterThings_BlossomCoin":  {
      "Name": "{{ModId}}_BlossomCoin",
    "DisplayName": "{{i18n:blossomcoin.name}}",
    "Description": "{{i18n:blossomcoin.description}}",
    "Type": "Minerals",
    "Category": -2,
    "Price": 750,
    "Texture": "{{InternalAssetKey: assets/blossom_coin.png}}",
    "Edibility": -300,
    "IsDrink": false,
    "Buffs": null,
    "GeodeDropsDefaultItems": false,
    "GeodeDrops": null,
    "ArtifactSpotChances": {
		"Beach": 0.05,
		"BusStop": 0.008,
		"Forest": 0.1,
		"Mountain": 0.02,
	    "Town": 0.04,
		"UndergroundMine": 0.1
	},
    "CanBeGivenAsGift": true,
    "CanBeTrashed": true,
    "ExcludeFromFishingCollection": false,
    "ExcludeFromShippingCollection": false,
    "ExcludeFromRandomSale": false,
    "ContextTags": [
      "color_pink",
	  "item_blossom_coin",
	  "blossom_coin"
    ],
    "CustomFields": null
         }
       }
     },
    {
	  "Logname": "Blue Egg, Blue Mayonnaise",
      "Action": "EditData",
      "Target": "Data/Objects",
      "Entries": {
        "maat.BetterThings_BlueEgg": {
          "Name": "{{ModId}}_BlueEgg",
          "Displayname": "{{i18n:blue_egg.name}}",
          "Description": "{{i18n:blue_egg.description}}",
          "Type": "Basic",
          "Category": -5,
          "Price": 50,
          "Texture": "{{InternalAssetKey: assets/blue_egg.png}}",
          "SpriteIndex": 0,
          "Edibility": 10,
          "IsDrink": false,
          "ContextTags": [
            "color_blue",
            "egg_item"
          ]
        },
        "maat.BetterThings_BigBlueEgg": {
          "Name": "{{ModId}}_BigBlueEgg",
          "Displayname": "{{i18n:big_blue_egg.name}}",
          "Description": "{{i18n:big_blue_egg.description}}",
          "Type": "Basic",
          "Category": -5,
          "Price": 100,
          "Texture": "{{InternalAssetKey: assets/big_blue_egg.png}}",
          "SpriteIndex": 0,
          "Edibility": 15,
          "IsDrink": false,
          "ContextTags": [
            "color_blue",
            "egg_item",
            "large_egg_item"
          ]
        },
		"maat.BetterThings_BlueMayonnaise": {
		  "Name": "{{ModId}}_BlueMayonnaise",
		  "Displayname": "{{i18n:bluemayonnaise.name}}",
		  "Description": "{{i18n:bluemayonnaise.description}}",
		  "Type": "Basic",
		  "Category": -26,
		  "Price": 750,
		  "Texture": "{{InternalAssetKey: assets/blue_mayonnaise.png}}",
		  "SpriteIndex": 0,
		  "Edibility": 25,
		  "IsDrink": true,
		  "ContextTags": [
			"color_blue",
			"mayo_item",
			"use_reverse_name_for_sorting"
		   ]
		}
      },
	  "When": { "BlueChickensHaveBlueEggsAndMayo": true }
    },
	{
	  "Logname": "Big Golden Egg, Golden Mayonnaise",
      "Action": "EditData",
      "Target": "Data/Objects",
      "Entries": {
        "maat.BetterThings_BigGoldenEgg": {
          "Name": "{{ModId}}_BigGoldenEgg",
          "Displayname": "{{i18n:biggolden_egg.name}}",
          "Description": "{{i18n:biggolden_egg.description}}",
          "Type": "Basic",
          "Category": -5,
          "Price": 600,
          "Texture": "{{InternalAssetKey: assets/biggolden_egg.png}}",
          "SpriteIndex": 0,
          "Edibility": 16,
          "IsDrink": false,
          "ContextTags": [
            "color_golden",
			"egg_item",
            "large_egg_item"
          ]
        },
		"maat.BetterThings_GoldenMayonnaise": {
		  "Name": "{{ModId}}_GoldenMayonnaise",
		  "Displayname": "{{i18n:goldenmayonnaise.name}}",
		  "Description": "{{i18n:goldenmayonnaise.description}}",
		  "Type": "Basic",
		  "Category": -26,
		  "Price": 850,
		  "Texture": "{{InternalAssetKey: assets/golden_mayonnaise.png}}",
		  "SpriteIndex": 0,
		  "Edibility": 29,
		  "IsDrink": true,
		  "ContextTags": [
			"color_golden",
			"mayo_item",
			"use_reverse_name_for_sorting"
		   ]
		}
      },
	  "When": { "GoldenChickensHaveBigGoldenEggsAndMayo": true }
    },
	 {
	  "Logname": "Ostrich Mayonnaise",
      "Action": "EditData",
      "Target": "Data/Objects",
      "Entries": {
		  "maat.BetterThings_OstrichMayonnaise": {
		  "Name": "{{ModId}}_OstrichMayonnaise",
		  "Displayname": "{{i18n:ostrichmayonnaise.name}}",
		  "Description": "{{i18n:ostrichmayonnaise.description}}",
		  "Type": "Basic",
		  "Category": -26,
		  "Price": 1050,
		  "Texture": "{{InternalAssetKey: assets/ostrich_mayonnaise.png}}",
		  "SpriteIndex": 0,
		  "Edibility": 55,
		  "IsDrink": true,
		  "ContextTags": [
			"color_white",
			"mayo_item",
			"use_reverse_name_for_sorting"
		   ]
		 }
	  },
	  "When": { "OstrichMayonnaise": true }
	},
	{
		"Action": "EditData",
        "Target": "Data/Objects",
        "Entries": {
		   "{{ModId}}_BlossomPotion":  {
	       "Name": "{{ModId}}_BlossomPotion",
           "DisplayName": "{{i18n:blossompotion.name}}",
           "Description": "{{i18n:blossompotion.description}}",
           "Type": "Basic",
           "Category": -26,
           "Price": 80000,
           "Texture": "{{InternalAssetKey: assets/blossom_potion.png}}",
           "SpriteIndex": 0,
           "Edibility": 75,
           "IsDrink": true,
           "Buffs": [
         {
           "Id": "Drink",
           "BuffId": null,
           "IconTexture": null,
           "IconSpriteIndex": 0,
           "Duration": 250,
           "IsDebuff": false,
           "GlowColor": null,
           "CustomAttributes": {
           "FarmingLevel": 5.0,
           "FishingLevel": 5.0,
           "MiningLevel": 0.0,
           "LuckLevel": 5.0,
           "ForagingLevel": 0.0,
           "MaxStamina": 125.0,
           "MagneticRadius": 100.0,
           "Speed": 1.0,
           "Defense": 10.0,
           "Attack": 20.0
         },
           "CustomFields": null
         }
       ],
           "GeodeDropsDefaultItems": false,
           "GeodeDrops": null,
           "ArtifactSpotChances": null,
           "CanBeGivenAsGift": true,
           "CanBeTrashed": true,
           "ExcludeFromFishingCollection": false,
           "ExcludeFromShippingCollection": false,
           "ExcludeFromRandomSale": false,
           "ContextTags": [
                "color_pink",
                "blossom_potion",
                "season_spring"
                          ],
              "CustomFields": null
         }
	   }
	 },
	 {
		"Action": "EditData",
        "Target": "Data/Objects",
        "Entries": {
		   "{{ModId}}_BlossomJuice":  {
	       "Name": "{{ModId}}_BlossomJuice",
           "DisplayName": "{{i18n:blossomjuice.name}}",
           "Description": "{{i18n:blossomjuice.description}}",
           "Type": "Basic",
           "Category": -26,
           "Price": 1500,
           "Texture": "{{InternalAssetKey: assets/blossom_juice.png}}",
           "SpriteIndex": 0,
           "Edibility": 22,
           "IsDrink": true,
           "Buffs": [
         {
           "Id": "Drink",
           "BuffId": null,
           "IconTexture": null,
           "IconSpriteIndex": 0,
           "Duration": 350,
           "IsDebuff": false,
           "GlowColor": null,
           "CustomAttributes": {
           "FarmingLevel": 0.0,
           "FishingLevel": 0.0,
           "MiningLevel": 0.0,
           "LuckLevel": 1.0,
           "ForagingLevel": 1.0,
           "MaxStamina": 15.0,
           "MagneticRadius": 160.0,
           "Speed": 2.0,
           "Defense": 0.0,
           "Attack": 1.0
         },
           "CustomFields": null
         }
       ],
           "GeodeDropsDefaultItems": false,
           "GeodeDrops": null,
           "ArtifactSpotChances": null,
           "CanBeGivenAsGift": true,
           "CanBeTrashed": true,
           "ExcludeFromFishingCollection": false,
           "ExcludeFromShippingCollection": false,
           "ExcludeFromRandomSale": false,
           "ContextTags": [
                "color_pink",
                "blossom_juice",
                "season_spring"
                          ],
              "CustomFields": null
         }
	   }
	 },
	 
	   // DESERT FESTIVAL FOODS
	 {
		"Action": "EditData",
        "Target": "Data/Objects",
        "Entries": {
		   "{{ModId}}_EarthyMousse":  {
	       "Name": "{{ModId}}_EarthyMousse",
           "DisplayName": "{{i18n:earthymousse.name}}",
           "Description": "{{i18n:earthymousse.description}}",
           "Type": "Cooking",
           "Category": -7,
           "Price": 300,
           "Texture": "TileSheets\\Objects_2",
           "SpriteIndex": 16,
           "Edibility": 38,
           "IsDrink": false,
           "Buffs": [
         {
           "Id": "Food",
           "BuffId": null,
           "IconTexture": null,
           "IconSpriteIndex": 0,
           "Duration": 550,
           "IsDebuff": false,
           "GlowColor": null,
           "CustomAttributes": {
           "FarmingLevel": 0.0,
           "FishingLevel": 0.0,
           "MiningLevel": 1.0,
           "LuckLevel": 0.0,
           "ForagingLevel": 0.0,
           "MaxStamina": 0.0,
           "MagneticRadius": 0.0,
           "Speed": 0.0,
           "Defense": 3.0,
           "Attack": 0.0
         },
           "CustomFields": null
         }
       ],
           "GeodeDropsDefaultItems": false,
           "GeodeDrops": null,
           "ArtifactSpotChances": null,
           "CanBeGivenAsGift": true,
           "CanBeTrashed": true,
           "ExcludeFromFishingCollection": false,
           "ExcludeFromShippingCollection": false,
           "ExcludeFromRandomSale": false,
           "ContextTags": [
                "color_brown",
                "season_spring"
             ],
              "CustomFields": null
         },
		 "{{ModId}}_SweetBeanCake":  {
	       "Name": "{{ModId}}_SweetBeanCake",
           "DisplayName": "{{i18n:sweetbeancake.name}}",
           "Description": "{{i18n:sweetbeancake.description}}",
           "Type": "Cooking",
           "Category": -7,
           "Price": 400,
           "Texture": "TileSheets\\Objects_2",
           "SpriteIndex": 17,
           "Edibility": 39,
           "IsDrink": false,
           "Buffs": [
         {
           "Id": "Food",
           "BuffId": null,
           "IconTexture": null,
           "IconSpriteIndex": 0,
           "Duration": 600,
           "IsDebuff": false,
           "GlowColor": null,
           "CustomAttributes": {
           "FarmingLevel": 0.0,
           "FishingLevel": 0.0,
           "MiningLevel": 0.0,
           "LuckLevel": 1.0,
           "ForagingLevel": 0.0,
           "MaxStamina": 0.0,
           "MagneticRadius": 0.0,
           "Speed": 0.0,
           "Defense": 3.0,
           "Attack": 0.0
         },
           "CustomFields": null
         }
       ],
           "GeodeDropsDefaultItems": false,
           "GeodeDrops": null,
           "ArtifactSpotChances": null,
           "CanBeGivenAsGift": true,
           "CanBeTrashed": true,
           "ExcludeFromFishingCollection": false,
           "ExcludeFromShippingCollection": false,
           "ExcludeFromRandomSale": false,
           "ContextTags": [
                "color_white",
                "season_spring"
             ],
              "CustomFields": null
         },
		 "{{ModId}}_SkullCaveCasserole":  {
	       "Name": "{{ModId}}_SkullCaveCasserole",
           "DisplayName": "{{i18n:skullcavecasserole.name}}",
           "Description": "{{i18n:skullcavecasserole.description}}",
           "Type": "Cooking",
           "Category": -7,
           "Price": 400,
           "Texture": "TileSheets\\Objects_2",
           "SpriteIndex": 18,
           "Edibility": 40,
           "IsDrink": false,
           "Buffs": [
         {
           "Id": "Food",
           "BuffId": null,
           "IconTexture": null,
           "IconSpriteIndex": 0,
           "Duration": 600,
           "IsDebuff": false,
           "GlowColor": null,
           "CustomAttributes": {
           "FarmingLevel": 0.0,
           "FishingLevel": 0.0,
           "MiningLevel": 0.0,
           "LuckLevel": 0.0,
           "ForagingLevel": 0.0,
           "MaxStamina": 0.0,
           "MagneticRadius": 0.0,
           "Speed": 0.0,
           "Defense": 3.0,
           "Attack": 1.0
         },
           "CustomFields": null
         }
       ],
           "GeodeDropsDefaultItems": false,
           "GeodeDrops": null,
           "ArtifactSpotChances": null,
           "CanBeGivenAsGift": true,
           "CanBeTrashed": true,
           "ExcludeFromFishingCollection": false,
           "ExcludeFromShippingCollection": false,
           "ExcludeFromRandomSale": false,
           "ContextTags": [
                "color_white",
                "season_spring"
             ],
              "CustomFields": null
         },
		 "{{ModId}}_SpicyTacos":  {
	       "Name": "{{ModId}}_SpicyTacos",
           "DisplayName": "{{i18n:spicytacos.name}}",
           "Description": "{{i18n:spicytacos.description}}",
           "Type": "Cooking",
           "Category": -7,
           "Price": 400,
           "Texture": "TileSheets\\Objects_2",
           "SpriteIndex": 19,
           "Edibility": 42,
           "IsDrink": false,
           "Buffs": [
         {
           "Id": "Food",
           "BuffId": null,
           "IconTexture": null,
           "IconSpriteIndex": 0,
           "Duration": 600,
           "IsDebuff": false,
           "GlowColor": null,
           "CustomAttributes": {
           "FarmingLevel": 0.0,
           "FishingLevel": 0.0,
           "MiningLevel": 0.0,
           "LuckLevel": 0.0,
           "ForagingLevel": 0.0,
           "MaxStamina": 0.0,
           "MagneticRadius": 0.0,
           "Speed": 1.0,
           "Defense": 3.0,
           "Attack": 0.0
         },
           "CustomFields": null
         }
       ],
           "GeodeDropsDefaultItems": false,
           "GeodeDrops": null,
           "ArtifactSpotChances": null,
           "CanBeGivenAsGift": true,
           "CanBeTrashed": true,
           "ExcludeFromFishingCollection": false,
           "ExcludeFromShippingCollection": false,
           "ExcludeFromRandomSale": false,
           "ContextTags": [
                "color_yellow",
                "season_spring"
             ],
              "CustomFields": null
         },
		 "{{ModId}}_MountainChili":  {
	       "Name": "{{ModId}}_MountainChili",
           "DisplayName": "{{i18n:mountainchili.name}}",
           "Description": "{{i18n:mountainchili.description}}",
           "Type": "Cooking",
           "Category": -7,
           "Price": 420,
           "Texture": "TileSheets\\Objects_2",
           "SpriteIndex": 20,
           "Edibility": 43,
           "IsDrink": false,
           "Buffs": [
         {
           "Id": "Food",
           "BuffId": null,
           "IconTexture": null,
           "IconSpriteIndex": 0,
           "Duration": 600,
           "IsDebuff": false,
           "GlowColor": null,
           "CustomAttributes": {
           "FarmingLevel": 0.0,
           "FishingLevel": 0.0,
           "MiningLevel": 3.0,
           "LuckLevel": 0.0,
           "ForagingLevel": 0.0,
           "MaxStamina": 0.0,
           "MagneticRadius": 0.0,
           "Speed": 0.0,
           "Defense": 1.0,
           "Attack": 0.0
         },
           "CustomFields": null
         }
       ],
           "GeodeDropsDefaultItems": false,
           "GeodeDrops": null,
           "ArtifactSpotChances": null,
           "CanBeGivenAsGift": true,
           "CanBeTrashed": true,
           "ExcludeFromFishingCollection": false,
           "ExcludeFromShippingCollection": false,
           "ExcludeFromRandomSale": false,
           "ContextTags": [
                "color_red",
                "season_spring"
             ],
              "CustomFields": null
         },
		 "{{ModId}}_CrystalCake":  {
	       "Name": "{{ModId}}_CrystalCake",
           "DisplayName": "{{i18n:crystalcake.name}}",
           "Description": "{{i18n:crystalcake.description}}",
           "Type": "Cooking",
           "Category": -7,
           "Price": 430,
           "Texture": "TileSheets\\Objects_2",
           "SpriteIndex": 21,
           "Edibility": 44,
           "IsDrink": false,
           "Buffs": [
         {
           "Id": "Food",
           "BuffId": null,
           "IconTexture": null,
           "IconSpriteIndex": 0,
           "Duration": 600,
           "IsDebuff": false,
           "GlowColor": null,
           "CustomAttributes": {
           "FarmingLevel": 0.0,
           "FishingLevel": 0.0,
           "MiningLevel": 3.0,
           "LuckLevel": 1.0,
           "ForagingLevel": 0.0,
           "MaxStamina": 0.0,
           "MagneticRadius": 0.0,
           "Speed": 0.0,
           "Defense": 0.0,
           "Attack": 0.0
         },
           "CustomFields": null
         }
       ],
           "GeodeDropsDefaultItems": false,
           "GeodeDrops": null,
           "ArtifactSpotChances": null,
           "CanBeGivenAsGift": true,
           "CanBeTrashed": true,
           "ExcludeFromFishingCollection": false,
           "ExcludeFromShippingCollection": false,
           "ExcludeFromRandomSale": false,
           "ContextTags": [
                "color_white",
                "season_spring"
             ],
              "CustomFields": null
         },
		 "{{ModId}}_CaveKebab":  {
	       "Name": "{{ModId}}_CaveKebab",
           "DisplayName": "{{i18n:cavekebab.name}}",
           "Description": "{{i18n:cavekebab.description}}",
           "Type": "Cooking",
           "Category": -7,
           "Price": 440,
           "Texture": "TileSheets\\Objects_2",
           "SpriteIndex": 22,
           "Edibility": 45,
           "IsDrink": false,
           "Buffs": [
         {
           "Id": "Food",
           "BuffId": null,
           "IconTexture": null,
           "IconSpriteIndex": 0,
           "Duration": 600,
           "IsDebuff": false,
           "GlowColor": null,
           "CustomAttributes": {
           "FarmingLevel": 0.0,
           "FishingLevel": 0.0,
           "MiningLevel": 3.0,
           "LuckLevel": 0.0,
           "ForagingLevel": 0.0,
           "MaxStamina": 0.0,
           "MagneticRadius": 0.0,
           "Speed": 0.0,
           "Defense": 0.0,
           "Attack": 1.0
         },
           "CustomFields": null
         }
       ],
           "GeodeDropsDefaultItems": false,
           "GeodeDrops": null,
           "ArtifactSpotChances": null,
           "CanBeGivenAsGift": true,
           "CanBeTrashed": true,
           "ExcludeFromFishingCollection": false,
           "ExcludeFromShippingCollection": false,
           "ExcludeFromRandomSale": false,
           "ContextTags": [
                "color_brown",
                "season_spring"
               ],
              "CustomFields": null
         },
		 "{{ModId}}_HotLog":  {
	       "Name": "{{ModId}}_HotLog",
           "DisplayName": "{{i18n:hotlog.name}}",
           "Description": "{{i18n:hotlog.description}}",
           "Type": "Cooking",
           "Category": -7,
           "Price": 450,
           "Texture": "TileSheets\\Objects_2",
           "SpriteIndex": 23,
           "Edibility": 45,
           "IsDrink": false,
           "Buffs": [
         {
           "Id": "Food",
           "BuffId": null,
           "IconTexture": null,
           "IconSpriteIndex": 0,
           "Duration": 600,
           "IsDebuff": false,
           "GlowColor": null,
           "CustomAttributes": {
           "FarmingLevel": 0.0,
           "FishingLevel": 0.0,
           "MiningLevel": 3.0,
           "LuckLevel": 0.0,
           "ForagingLevel": 0.0,
           "MaxStamina": 0.0,
           "MagneticRadius": 0.0,
           "Speed": 1.0,
           "Defense": 0.0,
           "Attack": 0.0
         },
           "CustomFields": null
         }
       ],
           "GeodeDropsDefaultItems": false,
           "GeodeDrops": null,
           "ArtifactSpotChances": null,
           "CanBeGivenAsGift": true,
           "CanBeTrashed": true,
           "ExcludeFromFishingCollection": false,
           "ExcludeFromShippingCollection": false,
           "ExcludeFromRandomSale": false,
           "ContextTags": [
                "color_red",
                "season_spring"
             ],
              "CustomFields": null
         },
		 "{{ModId}}_SourSalad":  {
	       "Name": "{{ModId}}_SourSalad",
           "DisplayName": "{{i18n:soursalad.name}}",
           "Description": "{{i18n:soursalad.description}}",
           "Type": "Cooking",
           "Category": -7,
           "Price": 460,
           "Texture": "TileSheets\\Objects_2",
           "SpriteIndex": 24,
           "Edibility": 46,
           "IsDrink": false,
           "Buffs": [
         {
           "Id": "Food",
           "BuffId": null,
           "IconTexture": null,
           "IconSpriteIndex": 0,
           "Duration": 600,
           "IsDebuff": false,
           "GlowColor": null,
           "CustomAttributes": {
           "FarmingLevel": 0.0,
           "FishingLevel": 0.0,
           "MiningLevel": 0.0,
           "LuckLevel": 3.0,
           "ForagingLevel": 0.0,
           "MaxStamina": 0.0,
           "MagneticRadius": 0.0,
           "Speed": 0.0,
           "Defense": 1.0,
           "Attack": 0.0
         },
           "CustomFields": null
         }
       ],
           "GeodeDropsDefaultItems": false,
           "GeodeDrops": null,
           "ArtifactSpotChances": null,
           "CanBeGivenAsGift": true,
           "CanBeTrashed": true,
           "ExcludeFromFishingCollection": false,
           "ExcludeFromShippingCollection": false,
           "ExcludeFromRandomSale": false,
           "ContextTags": [
                "color_green",
                "season_spring"
             ],
              "CustomFields": null
         },
		 "{{ModId}}_SuperfoodCake":  {
	       "Name": "{{ModId}}_SuperfoodCake",
           "DisplayName": "{{i18n:superfoodcake.name}}",
           "Description": "{{i18n:superfoodcake.description}}",
           "Type": "Cooking",
           "Category": -7,
           "Price": 470,
           "Texture": "TileSheets\\Objects_2",
           "SpriteIndex": 25,
           "Edibility": 47,
           "IsDrink": false,
           "Buffs": [
         {
           "Id": "Food",
           "BuffId": null,
           "IconTexture": null,
           "IconSpriteIndex": 0,
           "Duration": 600,
           "IsDebuff": false,
           "GlowColor": null,
           "CustomAttributes": {
           "FarmingLevel": 0.0,
           "FishingLevel": 0.0,
           "MiningLevel": 1.0,
           "LuckLevel": 3.0,
           "ForagingLevel": 0.0,
           "MaxStamina": 0.0,
           "MagneticRadius": 0.0,
           "Speed": 0.0,
           "Defense": 0.0,
           "Attack": 0.0
         },
           "CustomFields": null
         }
       ],
           "GeodeDropsDefaultItems": false,
           "GeodeDrops": null,
           "ArtifactSpotChances": null,
           "CanBeGivenAsGift": true,
           "CanBeTrashed": true,
           "ExcludeFromFishingCollection": false,
           "ExcludeFromShippingCollection": false,
           "ExcludeFromRandomSale": false,
           "ContextTags": [
                "color_white",
                "season_spring"
             ],
              "CustomFields": null
         },
		 "{{ModId}}_WarriorSmoothie":  {
	       "Name": "{{ModId}}_WarriorSmoothie",
           "DisplayName": "{{i18n:warriorsmoothie.name}}",
           "Description": "{{i18n:warriorsmoothie.description}}",
           "Type": "Cooking",
           "Category": -7,
           "Price": 480,
           "Texture": "TileSheets\\Objects_2",
           "SpriteIndex": 26,
           "Edibility": 48,
           "IsDrink": true,
           "Buffs": [
         {
           "Id": "Drink",
           "BuffId": null,
           "IconTexture": null,
           "IconSpriteIndex": 0,
           "Duration": 600,
           "IsDebuff": false,
           "GlowColor": null,
           "CustomAttributes": {
           "FarmingLevel": 0.0,
           "FishingLevel": 0.0,
           "MiningLevel": 0.0,
           "LuckLevel": 3.0,
           "ForagingLevel": 0.0,
           "MaxStamina": 0.0,
           "MagneticRadius": 0.0,
           "Speed": 0.0,
           "Defense": 0.0,
           "Attack": 1.0
         },
           "CustomFields": null
         }
       ],
           "GeodeDropsDefaultItems": false,
           "GeodeDrops": null,
           "ArtifactSpotChances": null,
           "CanBeGivenAsGift": true,
           "CanBeTrashed": true,
           "ExcludeFromFishingCollection": false,
           "ExcludeFromShippingCollection": false,
           "ExcludeFromRandomSale": false,
           "ContextTags": [
                "color_blue",
                "season_spring"
             ],
              "CustomFields": null
         },
		 "{{ModId}}_RumpledFruitSkin":  {
	       "Name": "{{ModId}}_RumpledFruitSkin",
           "DisplayName": "{{i18n:rumpledfruitskin.name}}",
           "Description": "{{i18n:rumpledfruitskin.description}}",
           "Type": "Cooking",
           "Category": -7,
           "Price": 490,
           "Texture": "TileSheets\\Objects_2",
           "SpriteIndex": 27,
           "Edibility": 49,
           "IsDrink": false,
           "Buffs": [
         {
           "Id": "Food",
           "BuffId": null,
           "IconTexture": null,
           "IconSpriteIndex": 0,
           "Duration": 600,
           "IsDebuff": false,
           "GlowColor": null,
           "CustomAttributes": {
           "FarmingLevel": 0.0,
           "FishingLevel": 0.0,
           "MiningLevel": 0.0,
           "LuckLevel": 3.0,
           "ForagingLevel": 0.0,
           "MaxStamina": 0.0,
           "MagneticRadius": 0.0,
           "Speed": 1.0,
           "Defense": 0.0,
           "Attack": 0.0
         },
           "CustomFields": null
         }
       ],
           "GeodeDropsDefaultItems": false,
           "GeodeDrops": null,
           "ArtifactSpotChances": null,
           "CanBeGivenAsGift": true,
           "CanBeTrashed": true,
           "ExcludeFromFishingCollection": false,
           "ExcludeFromShippingCollection": false,
           "ExcludeFromRandomSale": false,
           "ContextTags": [
                "color_yellow",
                "season_spring"
             ],
              "CustomFields": null
         },
		 "{{ModId}}_CalicoPizza":  {
	       "Name": "{{ModId}}_CalicoPizza",
           "DisplayName": "{{i18n:calicopizza.name}}",
           "Description": "{{i18n:calicopizza.description}}",
           "Type": "Cooking",
           "Category": -7,
           "Price": 500,
           "Texture": "TileSheets\\Objects_2",
           "SpriteIndex": 28,
           "Edibility": 50,
           "IsDrink": false,
           "Buffs": [
         {
           "Id": "Food",
           "BuffId": null,
           "IconTexture": null,
           "IconSpriteIndex": 0,
           "Duration": 600,
           "IsDebuff": false,
           "GlowColor": null,
           "CustomAttributes": {
           "FarmingLevel": 0.0,
           "FishingLevel": 0.0,
           "MiningLevel": 0.0,
           "LuckLevel": 0.0,
           "ForagingLevel": 0.0,
           "MaxStamina": 0.0,
           "MagneticRadius": 0.0,
           "Speed": 0.0,
           "Defense": 1.0,
           "Attack": 3.0
         },
           "CustomFields": null
         }
       ],
           "GeodeDropsDefaultItems": false,
           "GeodeDrops": null,
           "ArtifactSpotChances": null,
           "CanBeGivenAsGift": true,
           "CanBeTrashed": true,
           "ExcludeFromFishingCollection": false,
           "ExcludeFromShippingCollection": false,
           "ExcludeFromRandomSale": false,
           "ContextTags": [
                "color_yellow",
                "season_spring"
             ],
              "CustomFields": null
         },
		 "{{ModId}}_StuffedMushrooms":  {
	       "Name": "{{ModId}}_StuffedMushrooms",
           "DisplayName": "{{i18n:stuffedmushrooms.name}}",
           "Description": "{{i18n:stuffedmushrooms.description}}",
           "Type": "Cooking",
           "Category": -7,
           "Price": 510,
           "Texture": "TileSheets\\Objects_2",
           "SpriteIndex": 29,
           "Edibility": 51,
           "IsDrink": false,
           "Buffs": [
         {
           "Id": "Food",
           "BuffId": null,
           "IconTexture": null,
           "IconSpriteIndex": 0,
           "Duration": 600,
           "IsDebuff": false,
           "GlowColor": null,
           "CustomAttributes": {
           "FarmingLevel": 0.0,
           "FishingLevel": 0.0,
           "MiningLevel": 1.0,
           "LuckLevel": 0.0,
           "ForagingLevel": 0.0,
           "MaxStamina": 0.0,
           "MagneticRadius": 0.0,
           "Speed": 0.0,
           "Defense": 0.0,
           "Attack": 3.0
         },
           "CustomFields": null
         }
       ],
           "GeodeDropsDefaultItems": false,
           "GeodeDrops": null,
           "ArtifactSpotChances": null,
           "CanBeGivenAsGift": true,
           "CanBeTrashed": true,
           "ExcludeFromFishingCollection": false,
           "ExcludeFromShippingCollection": false,
           "ExcludeFromRandomSale": false,
           "ContextTags": [
                "color_brown",
                "season_spring"
             ],
              "CustomFields": null
         },
		 "{{ModId}}_ElfQuesadilla":  {
	       "Name": "{{ModId}}_ElfQuesadilla",
           "DisplayName": "{{i18n:elfquesadilla.name}}",
           "Description": "{{i18n:elfquesadilla.description}}",
           "Type": "Cooking",
           "Category": -7,
           "Price": 520,
           "Texture": "TileSheets\\Objects_2",
           "SpriteIndex": 30,
           "Edibility": 52,
           "IsDrink": false,
           "Buffs": [
         {
           "Id": "Food",
           "BuffId": null,
           "IconTexture": null,
           "IconSpriteIndex": 0,
           "Duration": 600,
           "IsDebuff": false,
           "GlowColor": null,
           "CustomAttributes": {
           "FarmingLevel": 0.0,
           "FishingLevel": 0.0,
           "MiningLevel": 0.0,
           "LuckLevel": 1.0,
           "ForagingLevel": 0.0,
           "MaxStamina": 0.0,
           "MagneticRadius": 0.0,
           "Speed": 0.0,
           "Defense": 0.0,
           "Attack": 3.0
         },
           "CustomFields": null
         }
       ],
           "GeodeDropsDefaultItems": false,
           "GeodeDrops": null,
           "ArtifactSpotChances": null,
           "CanBeGivenAsGift": true,
           "CanBeTrashed": true,
           "ExcludeFromFishingCollection": false,
           "ExcludeFromShippingCollection": false,
           "ExcludeFromRandomSale": false,
           "ContextTags": [
                "color_yellow",
                "season_spring"
             ],
              "CustomFields": null
         },
		 "{{ModId}}_NachosOfTheDesert":  {
	       "Name": "{{ModId}}_NachosOfTheDesert",
           "DisplayName": "{{i18n:nachosofthedesert.name}}",
           "Description": "{{i18n:nachosofthedesert.description}}",
           "Type": "Cooking",
           "Category": -7,
           "Price": 530,
           "Texture": "TileSheets\\Objects_2",
           "SpriteIndex": 31,
           "Edibility": 53,
           "IsDrink": false,
           "Buffs": [
         {
           "Id": "Food",
           "BuffId": null,
           "IconTexture": null,
           "IconSpriteIndex": 0,
           "Duration": 600,
           "IsDebuff": false,
           "GlowColor": null,
           "CustomAttributes": {
           "FarmingLevel": 0.0,
           "FishingLevel": 0.0,
           "MiningLevel": 0.0,
           "LuckLevel": 0.0,
           "ForagingLevel": 0.0,
           "MaxStamina": 0.0,
           "MagneticRadius": 0.0,
           "Speed": 1.0,
           "Defense": 0.0,
           "Attack": 3.0
         },
           "CustomFields": null
         }
       ],
           "GeodeDropsDefaultItems": false,
           "GeodeDrops": null,
           "ArtifactSpotChances": null,
           "CanBeGivenAsGift": true,
           "CanBeTrashed": true,
           "ExcludeFromFishingCollection": false,
           "ExcludeFromShippingCollection": false,
           "ExcludeFromRandomSale": false,
           "ContextTags": [
                "color_yellow",
                "season_spring"
             ],
              "CustomFields": null
         },
		 "{{ModId}}_Cioppino":  {
	       "Name": "{{ModId}}_Cioppino",
           "DisplayName": "{{i18n:cioppino.name}}",
           "Description": "{{i18n:cioppino.description}}",
           "Type": "Cooking",
           "Category": -7,
           "Price": 540,
           "Texture": "TileSheets\\Objects_2",
           "SpriteIndex": 32,
           "Edibility": 54,
           "IsDrink": false,
           "Buffs": [
         {
           "Id": "Food",
           "BuffId": null,
           "IconTexture": null,
           "IconSpriteIndex": 0,
           "Duration": 600,
           "IsDebuff": false,
           "GlowColor": null,
           "CustomAttributes": {
           "FarmingLevel": 0.0,
           "FishingLevel": 3.0,
           "MiningLevel": 0.0,
           "LuckLevel": 0.0,
           "ForagingLevel": 0.0,
           "MaxStamina": 0.0,
           "MagneticRadius": 0.0,
           "Speed": 0.0,
           "Defense": 1.0,
           "Attack": 0.0
         },
           "CustomFields": null
         }
       ],
           "GeodeDropsDefaultItems": false,
           "GeodeDrops": null,
           "ArtifactSpotChances": null,
           "CanBeGivenAsGift": true,
           "CanBeTrashed": true,
           "ExcludeFromFishingCollection": false,
           "ExcludeFromShippingCollection": false,
           "ExcludeFromRandomSale": false,
           "ContextTags": [
                "color_red",
                "season_spring"
             ],
              "CustomFields": null
         },
		 "{{ModId}}_RainforestShrimp":  {
	       "Name": "{{ModId}}_RainforestShrimp",
           "DisplayName": "{{i18n:rainforestshrimp.name}}",
           "Description": "{{i18n:rainforestshrimp.description}}",
           "Type": "Cooking",
           "Category": -7,
           "Price": 550,
           "Texture": "TileSheets\\Objects_2",
           "SpriteIndex": 33,
           "Edibility": 55,
           "IsDrink": false,
           "Buffs": [
         {
           "Id": "Food",
           "BuffId": null,
           "IconTexture": null,
           "IconSpriteIndex": 0,
           "Duration": 600,
           "IsDebuff": false,
           "GlowColor": null,
           "CustomAttributes": {
           "FarmingLevel": 0.0,
           "FishingLevel": 3.0,
           "MiningLevel": 1.0,
           "LuckLevel": 0.0,
           "ForagingLevel": 0.0,
           "MaxStamina": 0.0,
           "MagneticRadius": 0.0,
           "Speed": 0.0,
           "Defense": 0.0,
           "Attack": 0.0
         },
           "CustomFields": null
         }
       ],
           "GeodeDropsDefaultItems": false,
           "GeodeDrops": null,
           "ArtifactSpotChances": null,
           "CanBeGivenAsGift": true,
           "CanBeTrashed": true,
           "ExcludeFromFishingCollection": false,
           "ExcludeFromShippingCollection": false,
           "ExcludeFromRandomSale": false,
           "ContextTags": [
                "color_green",
                "season_spring"
             ],
              "CustomFields": null
         },
		 "{{ModId}}_ShrimpDonut":  {
	       "Name": "{{ModId}}_ShrimpDonut",
           "DisplayName": "{{i18n:shrimpdonut.name}}",
           "Description": "{{i18n:shrimpdonut.description}}",
           "Type": "Cooking",
           "Category": -7,
           "Price": 560,
           "Texture": "TileSheets\\Objects_2",
           "SpriteIndex": 34,
           "Edibility": 56,
           "IsDrink": false,
           "Buffs": [
         {
           "Id": "Food",
           "BuffId": null,
           "IconTexture": null,
           "IconSpriteIndex": 0,
           "Duration": 600,
           "IsDebuff": false,
           "GlowColor": null,
           "CustomAttributes": {
           "FarmingLevel": 0.0,
           "FishingLevel": 3.0,
           "MiningLevel": 0.0,
           "LuckLevel": 1.0,
           "ForagingLevel": 0.0,
           "MaxStamina": 0.0,
           "MagneticRadius": 0.0,
           "Speed": 0.0,
           "Defense": 0.0,
           "Attack": 0.0
         },
           "CustomFields": null
         }
       ],
           "GeodeDropsDefaultItems": false,
           "GeodeDrops": null,
           "ArtifactSpotChances": null,
           "CanBeGivenAsGift": true,
           "CanBeTrashed": true,
           "ExcludeFromFishingCollection": false,
           "ExcludeFromShippingCollection": false,
           "ExcludeFromRandomSale": false,
           "ContextTags": [
                "color_orange",
                "season_spring"
             ],
              "CustomFields": null
         },
		 "{{ModId}}_SmellOfTheSea":  {
	       "Name": "{{ModId}}_SmellOfTheSea",
           "DisplayName": "{{i18n:smellofthesea.name}}",
           "Description": "{{i18n:smellofthesea.description}}",
           "Type": "Cooking",
           "Category": -7,
           "Price": 570,
           "Texture": "TileSheets\\Objects_2",
           "SpriteIndex": 35,
           "Edibility": 57,
           "IsDrink": false,
           "Buffs": [
         {
           "Id": "Food",
           "BuffId": null,
           "IconTexture": null,
           "IconSpriteIndex": 0,
           "Duration": 600,
           "IsDebuff": false,
           "GlowColor": null,
           "CustomAttributes": {
           "FarmingLevel": 0.0,
           "FishingLevel": 3.0,
           "MiningLevel": 0.0,
           "LuckLevel": 0.0,
           "ForagingLevel": 0.0,
           "MaxStamina": 0.0,
           "MagneticRadius": 0.0,
           "Speed": 0.0,
           "Defense": 0.0,
           "Attack": 1.0
         },
           "CustomFields": null
         }
       ],
           "GeodeDropsDefaultItems": false,
           "GeodeDrops": null,
           "ArtifactSpotChances": null,
           "CanBeGivenAsGift": true,
           "CanBeTrashed": true,
           "ExcludeFromFishingCollection": false,
           "ExcludeFromShippingCollection": false,
           "ExcludeFromRandomSale": false,
           "ContextTags": [
                "color_blue",
                "season_spring"
             ],
              "CustomFields": null
         },
		 "{{ModId}}_DesertGumbo":  {
	       "Name": "{{ModId}}_DesertGumbo",
           "DisplayName": "{{i18n:desertgumbo.name}}",
           "Description": "{{i18n:desertgumbo.description}}",
           "Type": "Cooking",
           "Category": -7,
           "Price": 580,
           "Texture": "TileSheets\\Objects_2",
           "SpriteIndex": 36,
           "Edibility": 58,
           "IsDrink": false,
           "Buffs": [
         {
           "Id": "Food",
           "BuffId": null,
           "IconTexture": null,
           "IconSpriteIndex": 0,
           "Duration": 600,
           "IsDebuff": false,
           "GlowColor": null,
           "CustomAttributes": {
           "FarmingLevel": 0.0,
           "FishingLevel": 3.0,
           "MiningLevel": 0.0,
           "LuckLevel": 0.0,
           "ForagingLevel": 0.0,
           "MaxStamina": 0.0,
           "MagneticRadius": 0.0,
           "Speed": 1.0,
           "Defense": 0.0,
           "Attack": 0.0
         },
           "CustomFields": null
         }
       ],
           "GeodeDropsDefaultItems": false,
           "GeodeDrops": null,
           "ArtifactSpotChances": null,
           "CanBeGivenAsGift": true,
           "CanBeTrashed": true,
           "ExcludeFromFishingCollection": false,
           "ExcludeFromShippingCollection": false,
           "ExcludeFromRandomSale": false,
           "ContextTags": [
                "color_yellow",
                "season_spring"
             ],
              "CustomFields": null
         }
	   },
	   "When": { "DesertFestivalFoods": true }
	 }
   ]
}